pymvg/__init__.py
pymvg/align.py
pymvg/calibration.py
pymvg/camera_model.py
pymvg/multi_camera_system.py
pymvg/plot_utils.py
pymvg/quaternions.py
pymvg/ros_compat.py
pymvg/util.py
pymvg/extern/__init__.py
pymvg/extern/opencv/__init__.py
pymvg/extern/opencv/npcv.py
pymvg/extern/ros/__init__.py
pymvg/extern/ros/ros_publisher.py
pymvg/extern/ros/rviz_utils.py
pymvg-2.1.0.dist-info/LICENSE.txt
pymvg-2.1.0.dist-info/METADATA
pymvg-2.1.0.dist-info/WHEEL
pymvg-2.1.0.dist-info/top_level.txt
pymvg-2.1.0.dist-info/RECORD
