Metadata-Version: 2.1
Name: pymvg
Version: 2.1.0
Summary: Python Multi-View Geometry
Author-email: Andrew Straw <strawman@astraw.com>
License: pymvg
Project-URL: homepage, https://github.com/strawlab/pymvg
Requires-Python: >=3.8
License-File: LICENSE.txt
Requires-Dist: PyYAML (>=5.1)
Requires-Dist: numpy
Requires-Dist: matplotlib
Requires-Dist: multicamselfcal (>=0.2.1)
